simulated_annealing/__init__.py
simulated_annealing/optimize.py
simulated_annealing-0.4.0.dist-info/LICENSE
simulated_annealing-0.4.0.dist-info/METADATA
simulated_annealing-0.4.0.dist-info/WHEEL
simulated_annealing-0.4.0.dist-info/top_level.txt
simulated_annealing-0.4.0.dist-info/RECORD
