Metadata-Version: 2.1
Name: simulated-annealing
Version: 0.4.0
Summary: A Simulated Annealing implimentation with a scikit-learn style API backed by joblib for speed.
Home-page: https://github.com/skylergrammer/SimulatedAnnealing
Author: Skyler Grammer, Andrew Nystrom
Author-email: skylergrammer@gmail.com, awnystrom@gmail.com
License: Apache 2.0
Keywords: simulated,annealing,parameter,hyperparameter,optimization,optimisation,model,selection
Platform: UNKNOWN
Classifier: Programming Language :: Python
Classifier: Programming Language :: Python :: 3
Classifier: Programming Language :: Python :: 3.6
Classifier: License :: OSI Approved :: Apache Software License
Classifier: Operating System :: OS Independent
Classifier: Development Status :: 4 - Beta
Classifier: Intended Audience :: Developers
Requires-Dist: scikit-learn (>=0.16.0)
Requires-Dist: numpy (>=1.9.0)
Requires-Dist: joblib (>=0.17.0)
